{"words": [{"word": "he", "start_time ": 0.0, "duration": 1.8}, {"word": "finishes", "start_time ": 1.84, "duration": 0.86}, {"word": "the", "start_time ": 2.74, "duration": 0.16}, {"word": "antietam", "start_time ": 3.0, "duration": 1.2}, {"word": "is", "start_time ": 4.44, "duration": 0.24}, {"word": "a", "start_time ": 4.8, "duration": 0.12}, {"word": "ute", "start_time ": 5.06, "duration": 0.52}, {"word": "etain", "start_time ": 5.64, "duration": 0.9}, {"word": "the", "start_time ": 6.56, "duration": 0.1}, {"word": "fine", "start_time ": 6.68, "duration": 0.3}], "confidence": 4.5160293025084}
