{"words": [{"word": "the", "start_time ": 0.0, "duration": 1.0}, {"word": "camel", "start_time ": 1.06, "duration": 0.42}, {"word": "driver", "start_time ": 1.62, "duration": 0.44}, {"word": "though", "start_time ": 2.28, "duration": 0.82}, {"word": "seemed", "start_time ": 3.14, "duration": 0.62}, {"word": "not", "start_time ": 3.78, "duration": 0.32}, {"word": "to", "start_time ": 4.1, "duration": 0.08}, {"word": "be", "start_time ": 4.3, "duration": 0.2}, {"word": "very", "start_time ": 4.5, "duration": 0.52}, {"word": "concerned", "start_time ": 5.02, "duration": 1.26}, {"word": "with", "start_time ": 6.32, "duration": 0.18}, {"word": "the", "start_time ": 6.5, "duration": 0.2}, {"word": "threat", "start_time ": 6.7, "duration": 0.38}, {"word": "of", "start_time ": 7.14, "duration": 0.2}, {"word": "war", "start_time ": 7.48, "duration": 0.18}], "confidence": -72.42105100636388}
