{"words": [{"word": "the", "start_time ": 0.0, "duration": 1.52}, {"word": "tigress", "start_time ": 1.52, "duration": 0.78}, {"word": "into", "start_time ": 2.38, "duration": 0.26}, {"word": "the", "start_time ": 2.66, "duration": 0.14}, {"word": "story", "start_time ": 2.82, "duration": 0.76}, {"word": "at", "start_time ": 3.7, "duration": 0.08}, {"word": "the", "start_time ": 3.78, "duration": 0.14}, {"word": "mines", "start_time ": 3.92, "duration": 1.62}], "confidence": -17.034340629002884}
