{"words": [{"word": "a", "start_time ": 0.0, "duration": 0.64}, {"word": "line", "start_time ": 0.72, "duration": 0.34}, {"word": "of", "start_time ": 1.06, "duration": 0.18}, {"word": "blame", "start_time ": 1.28, "duration": 0.42}, {"word": "high", "start_time ": 1.78, "duration": 0.32}, {"word": "can", "start_time ": 2.16, "duration": 0.18}, {"word": "be", "start_time ": 2.38, "duration": 0.16}, {"word": "seen", "start_time ": 2.58, "duration": 0.3}, {"word": "in", "start_time ": 2.88, "duration": 0.2}, {"word": "the", "start_time ": 3.12, "duration": 0.22}, {"word": "atmosphere", "start_time ": 3.46, "duration": 0.76}], "confidence": -37.04334538259212}
