{"words": [{"word": "our", "start_time ": 0.0, "duration": 1.0}, {"word": "lord", "start_time ": 1.06, "duration": 0.8}, {"word": "really", "start_time ": 1.9, "duration": 0.58}, {"word": "is", "start_time ": 2.48, "duration": 0.32}, {"word": "look", "start_time ": 2.84, "duration": 0.26}, {"word": "for", "start_time ": 3.12, "duration": 0.22}, {"word": "for", "start_time ": 3.34, "duration": 0.2}, {"word": "the", "start_time ": 3.56, "duration": 0.18}, {"word": "word", "start_time ": 3.78, "duration": 0.1}], "confidence": -29.261532743120455}
