{"words": [{"word": "there", "start_time ": 0.0, "duration": 0.74}, {"word": "were", "start_time ": 0.74, "duration": 0.14}, {"word": "looking", "start_time ": 0.9, "duration": 0.26}, {"word": "on", "start_time ": 1.16, "duration": 0.16}, {"word": "the", "start_time ": 1.32, "duration": 0.12}, {"word": "fore", "start_time ": 1.46, "duration": 0.18}, {"word": "god", "start_time ": 1.7, "duration": 0.2}, {"word": "his", "start_time ": 1.94, "duration": 0.16}, {"word": "companion", "start_time ": 2.14, "duration": 0.5}, {"word": "and", "start_time ": 2.7, "duration": 0.08}, {"word": "with", "start_time ": 2.84, "duration": 0.14}], "confidence": -57.37694758932703}
