{"words": [{"word": "you", "start_time ": 0.0, "duration": 0.52}, {"word": "would", "start_time ": 0.6, "duration": 0.22}, {"word": "have", "start_time ": 0.82, "duration": 0.18}, {"word": "to", "start_time ": 1.08, "duration": 0.14}, {"word": "have", "start_time ": 2.18, "duration": 0.46}, {"word": "been", "start_time ": 2.64, "duration": 0.2}, {"word": "born", "start_time ": 2.98, "duration": 0.24}, {"word": "on", "start_time ": 3.22, "duration": 0.18}, {"word": "arab", "start_time ": 3.42, "duration": 0.54}, {"word": "to", "start_time ": 4.02, "duration": 0.14}, {"word": "understand", "start_time ": 4.18, "duration": 0.66}, {"word": "he", "start_time ": 4.96, "duration": 0.5}, {"word": "answered", "start_time ": 5.46, "duration": 0.44}], "confidence": -56.54970317473317}
