{"words": [{"word": "your", "start_time ": 0.0, "duration": 1.2}, {"word": "sudden", "start_time ": 1.24, "duration": 0.32}, {"word": "went", "start_time ": 1.58, "duration": 0.26}, {"word": "to", "start_time ": 1.86, "duration": 0.22}, {"word": "serve", "start_time ": 2.14, "duration": 0.46}, {"word": "at", "start_time ": 2.6, "duration": 0.32}, {"word": "the", "start_time ": 2.92, "duration": 0.2}, {"word": "temple", "start_time ": 3.14, "duration": 1.36}, {"word": "and", "start_time ": 4.62, "duration": 0.12}, {"word": "became", "start_time ": 4.8, "duration": 0.46}, {"word": "essential", "start_time ": 5.26, "duration": 1.08}], "confidence": -28.378793764264145}
