{"words": [{"word": "he", "start_time ": 0.0, "duration": 0.96}, {"word": "saw", "start_time ": 0.96, "duration": 0.26}, {"word": "that", "start_time ": 1.22, "duration": 0.18}, {"word": "pasty", "start_time ": 1.52, "duration": 0.42}, {"word": "mass", "start_time ": 1.98, "duration": 0.28}, {"word": "eyes", "start_time ": 2.44, "duration": 0.3}, {"word": "were", "start_time ": 2.78, "duration": 0.2}, {"word": "filled", "start_time ": 3.04, "duration": 0.32}, {"word": "with", "start_time ": 3.42, "duration": 0.26}, {"word": "tears", "start_time ": 3.74, "duration": 0.36}], "confidence": -44.27546948649086}
