{"words": [{"word": "i", "start_time ": 0.0, "duration": 1.78}, {"word": "tied", "start_time ": 1.82, "duration": 0.5}, {"word": "on", "start_time ": 2.42, "duration": 0.1}, {"word": "the", "start_time ": 2.54, "duration": 0.12}, {"word": "last", "start_time ": 2.68, "duration": 0.32}, {"word": "evening", "start_time ": 3.08, "duration": 0.56}, {"word": "seadrift", "start_time ": 3.64, "duration": 1.34}, {"word": "the", "start_time ": 5.02, "duration": 0.1}, {"word": "general", "start_time ": 5.12, "duration": 0.2}], "confidence": 9.558656159337588}
