{"words": [{"word": "who", "start_time ": 0.0, "duration": 1.18}, {"word": "are", "start_time ": 1.18, "duration": 0.34}, {"word": "you", "start_time ": 1.56, "duration": 0.16}, {"word": "to", "start_time ": 1.76, "duration": 0.26}, {"word": "get", "start_time ": 2.04, "duration": 0.28}, {"word": "talk", "start_time ": 2.32, "duration": 0.3}, {"word": "with", "start_time ": 2.66, "duration": 0.26}, {"word": "any", "start_time ": 3.06, "duration": 0.24}, {"word": "of", "start_time ": 3.38, "duration": 0.12}, {"word": "them", "start_time ": 3.52, "duration": 0.12}], "confidence": -37.21876203049045}
