{"words": [{"word": "he", "start_time ": 0.0, "duration": 0.58}, {"word": "didn't", "start_time ": 0.58, "duration": 0.38}, {"word": "like", "start_time ": 1.16, "duration": 0.28}, {"word": "to", "start_time ": 1.46, "duration": 0.14}, {"word": "cry", "start_time ": 1.6, "duration": 0.44}, {"word": "with", "start_time ": 2.04, "duration": 0.38}, {"word": "other", "start_time ": 2.5, "duration": 0.22}, {"word": "people", "start_time ": 2.74, "duration": 0.28}, {"word": "that", "start_time ": 3.2, "duration": 0.24}], "confidence": -33.48829413418737}
