{"words": [{"word": "if", "start_time ": 0.0, "duration": 0.88}, {"word": "he", "start_time ": 0.88, "duration": 0.16}, {"word": "abandons", "start_time ": 1.06, "duration": 0.9}, {"word": "the", "start_time ": 2.0, "duration": 0.1}, {"word": "pursue", "start_time ": 2.22, "duration": 0.66}, {"word": "its", "start_time ": 3.0, "duration": 0.18}, {"word": "because", "start_time ": 3.24, "duration": 0.76}, {"word": "wasn't", "start_time ": 4.08, "duration": 0.44}, {"word": "rude", "start_time ": 4.56, "duration": 0.4}], "confidence": -32.70830560713668}
