{"words": [{"word": "i", "start_time ": 0.0, "duration": 1.58}, {"word": "really", "start_time ": 1.68, "duration": 0.42}, {"word": "hope", "start_time ": 2.1, "duration": 0.22}, {"word": "i", "start_time ": 2.38, "duration": 0.08}, {"word": "can", "start_time ": 2.48, "duration": 0.26}, {"word": "earn", "start_time ": 2.76, "duration": 0.24}, {"word": "a", "start_time ": 3.08, "duration": 0.06}, {"word": "batch", "start_time ": 3.14, "duration": 0.28}, {"word": "for", "start_time ": 3.46, "duration": 0.14}, {"word": "punishing", "start_time ": 3.62, "duration": 0.34}, {"word": "the", "start_time ": 3.96, "duration": 0.12}, {"word": "class", "start_time ": 4.1, "duration": 0.24}], "confidence": -51.629028677270014}
