{"words": [{"word": "the", "start_time ": 0.0, "duration": 0.98}, {"word": "caller", "start_time ": 1.06, "duration": 0.5}, {"word": "incredible", "start_time ": 1.66, "duration": 0.52}, {"word": "tone", "start_time ": 2.18, "duration": 0.48}, {"word": "at", "start_time ": 2.74, "duration": 0.08}, {"word": "the", "start_time ": 2.84, "duration": 0.12}, {"word": "time", "start_time ": 2.96, "duration": 0.34}, {"word": "that", "start_time ": 3.34, "duration": 0.16}, {"word": "one", "start_time ": 3.58, "duration": 0.38}, {"word": "to", "start_time ": 4.0, "duration": 0.12}, {"word": "hear", "start_time ": 4.16, "duration": 0.22}, {"word": "them", "start_time ": 4.44, "duration": 0.08}], "confidence": -39.852457362935866}
