{"words": [{"word": "you", "start_time ": 0.0, "duration": 1.2}, {"word": "won't", "start_time ": 1.22, "duration": 0.2}, {"word": "be", "start_time ": 1.48, "duration": 0.16}, {"word": "saved", "start_time ": 1.68, "duration": 0.32}, {"word": "it", "start_time ": 2.02, "duration": 0.2}, {"word": "till", "start_time ": 2.26, "duration": 0.16}, {"word": "the", "start_time ": 2.46, "duration": 0.12}, {"word": "money", "start_time ": 2.58, "duration": 0.26}, {"word": "is", "start_time ": 2.86, "duration": 0.1}, {"word": "in", "start_time ": 2.96, "duration": 0.12}, {"word": "overhand", "start_time ": 3.1, "duration": 0.64}], "confidence": -43.520114490556224}
