{"words": [{"word": "the", "start_time ": 0.0, "duration": 0.82}, {"word": "flop", "start_time ": 0.82, "duration": 0.34}, {"word": "castlemon", "start_time ": 1.2, "duration": 0.56}, {"word": "as", "start_time ": 1.82, "duration": 0.14}, {"word": "land", "start_time ": 2.0, "duration": 0.22}, {"word": "italy", "start_time ": 2.26, "duration": 0.52}, {"word": "on", "start_time ": 2.84, "duration": 0.12}, {"word": "their", "start_time ": 2.98, "duration": 0.12}, {"word": "right", "start_time ": 3.12, "duration": 0.18}, {"word": "were", "start_time ": 3.34, "duration": 0.18}, {"word": "oiled", "start_time ": 3.58, "duration": 0.44}], "confidence": -15.22550912915375}
