{"words": [{"word": "palmer", "start_time ": 0.0, "duration": 1.68}, {"word": "concha", "start_time ": 1.76, "duration": 0.72}, {"word": "sitting", "start_time ": 2.54, "duration": 0.34}, {"word": "again", "start_time ": 3.0, "duration": 0.4}, {"word": "for", "start_time ": 3.42, "duration": 0.26}, {"word": "the", "start_time ": 3.72, "duration": 0.24}, {"word": "weekend", "start_time ": 3.96, "duration": 0.54}, {"word": "if", "start_time ": 4.6, "duration": 0.08}, {"word": "you", "start_time ": 4.7, "duration": 0.16}, {"word": "want", "start_time ": 4.88, "duration": 0.2}, {"word": "to", "start_time ": 5.1, "duration": 0.12}, {"word": "come", "start_time ": 5.22, "duration": 0.24}, {"word": "more", "start_time ": 5.52, "duration": 0.18}], "confidence": -57.827309320691086}
