{"words": [{"word": "i'll", "start_time ": 0.0, "duration": 0.66}, {"word": "give", "start_time ": 0.68, "duration": 0.18}, {"word": "them", "start_time ": 0.88, "duration": 0.2}, {"word": "was", "start_time ": 1.14, "duration": 0.52}, {"word": "the", "start_time ": 1.7, "duration": 0.16}, {"word": "one", "start_time ": 1.9, "duration": 0.6}, {"word": "and", "start_time ": 2.6, "duration": 0.1}, {"word": "then", "start_time ": 2.7, "duration": 0.22}, {"word": "there", "start_time ": 2.94, "duration": 0.22}, {"word": "were", "start_time ": 3.18, "duration": 0.12}], "confidence": -37.016178251563076}
