{"words": [{"word": "other", "start_time ": 0.0, "duration": 0.92}, {"word": "servants", "start_time ": 0.94, "duration": 0.6}, {"word": "maintained", "start_time ": 1.56, "duration": 0.5}, {"word": "the", "start_time ": 2.08, "duration": 0.22}, {"word": "fat", "start_time ": 2.3, "duration": 0.42}, {"word": "in", "start_time ": 2.84, "duration": 0.12}, {"word": "the", "start_time ": 3.0, "duration": 0.14}, {"word": "hocus", "start_time ": 3.18, "duration": 0.38}], "confidence": -45.98871992213054}
