{"words": [{"word": "not", "start_time ": 0.0, "duration": 0.9}, {"word": "that", "start_time ": 0.92, "duration": 0.14}, {"word": "i", "start_time ": 1.06, "duration": 0.02}, {"word": "was", "start_time ": 1.22, "duration": 0.28}, {"word": "listening", "start_time ": 1.5, "duration": 0.4}, {"word": "but", "start_time ": 2.06, "duration": 0.18}, {"word": "i", "start_time ": 2.26, "duration": 0.02}, {"word": "always", "start_time ": 2.38, "duration": 0.32}, {"word": "said", "start_time ": 2.7, "duration": 0.22}, {"word": "you", "start_time ": 2.96, "duration": 0.08}, {"word": "are", "start_time ": 3.1, "duration": 0.42}, {"word": "really", "start_time ": 3.54, "duration": 0.34}, {"word": "stress", "start_time ": 3.88, "duration": 0.4}, {"word": "when", "start_time ": 4.3, "duration": 0.18}, {"word": "you", "start_time ": 4.52, "duration": 0.18}, {"word": "work", "start_time ": 4.74, "duration": 0.24}, {"word": "plain", "start_time ": 5.02, "duration": 0.24}, {"word": "in", "start_time ": 5.28, "duration": 0.04}, {"word": "the", "start_time ": 5.34, "duration": 0.12}, {"word": "stution", "start_time ": 5.46, "duration": 0.5}, {"word": "the", "start_time ": 5.96, "duration": 0.06}], "confidence": -80.49357363276124}
